progbarr/__init__.py
progbarr/progressbar.py
progbarr-2.0.0.dist-info/licenses/LICENSE
progbarr-2.0.0.dist-info/METADATA
progbarr-2.0.0.dist-info/WHEEL
progbarr-2.0.0.dist-info/top_level.txt
progbarr-2.0.0.dist-info/RECORD
