Metadata-Version: 2.4
Name: progbarr
Version: 2.0.0
Summary: Progbarr is a Python library for creating highly performant and customizable progress bars in the console.
Author-email: "Haripo Wesley T." <haripowesleyt@proton.me>
Maintainer-email: "Haripo Wesley T." <haripowesleyt@proton.me>
License: MIT License
Project-URL: Homepage, https://github.com/haripowesleyt/progbarr
Project-URL: Issues, https://github.com/haripowesleyt/progbarr/issues
Project-URL: Repository, https://github.com/haripowesleyt/progbarr
Keywords: progress,progress bar
Classifier: Development Status :: 5 - Production/Stable
Classifier: Intended Audience :: Developers
Classifier: Programming Language :: Python :: 3.7
Classifier: Programming Language :: Python :: 3.8
Classifier: Programming Language :: Python :: 3.9
Classifier: Programming Language :: Python :: 3.10
Classifier: Programming Language :: Python :: 3.11
Classifier: Programming Language :: Python :: 3.12
Classifier: Programming Language :: Python :: 3.13
Classifier: License :: OSI Approved :: MIT License
Classifier: Operating System :: OS Independent
Requires-Python: >=3.7
License-File: LICENSE
Dynamic: license-file
